{
  "replace": false,
  "slots": [
    "armor/helmet/plate2"
  ],
  "materialSlotCount": 1,
  "displayType": "major",
  "glyph": {
    "textureX": 99,
    "textureY": 35
  },
  "outcomes": [
    {
      "material": {
        "item": "minecraft:diamond",
        "count": 1
      },
      "requiredCapabilities": {
        "hammer": 3
      },
      "moduleKey": "armor/helmet/plate2",
      "moduleVariant": "armor/helmet/plate2/diamond"
    },
    {
      "material": {
        "item": "minecraft:iron_ingot",
        "count": 1
      },
      "requiredCapabilities": {
        "hammer": 2
      },
      "moduleKey": "armor/helmet/plate2",
      "moduleVariant": "armor/helmet/plate2/iron_ingot"
    },
    {
      "material": {
        "item": "minecraft:gold_ingot",
        "count": 1
      },
      "requiredCapabilities": {
        "hammer": 1
      },
      "moduleKey": "armor/helmet/plate2",
      "moduleVariant": "armor/helmet/plate2/gold_ingot"
    },
    {
      "material": {
        "item": "minecraft:leather",
        "count": 1
      },
      "requiredCapabilities": {
        "cut": 2
      },
      "moduleKey": "armor/helmet/plate2",
      "moduleVariant": "armor/helmet/plate2/leather"
    },
    {
      "material": {
        "item": "minecraft:rabbit_hide",
        "count": 1
      },
      "requiredCapabilities": {
        "cut": 2
      },
      "moduleKey": "armor/helmet/plate2",
      "moduleVariant": "armor/helmet/plate2/hide"
    },
    {
      "material": {
        "item": "minecraft:cactus",
        "count": 1
      },
      "requiredCapabilities": {
        "cut": 2
      },
      "moduleKey": "armor/helmet/plate2",
      "moduleVariant": "armor/helmet/plate2/cactus"
    },
    {
      "material": {
        "item": "minecraft:prismarine_shard",
        "count": 1
      },
      "requiredCapabilities": {
        "hammer": 2
      },
      "moduleKey": "armor/helmet/plate2",
      "moduleVariant": "armor/helmet/plate2/prismarine"
    }
  ]
}